uvhow/__init__.py
uvhow/__main__.py
uvhow-0.4.3.dist-info/WHEEL
uvhow-0.4.3.dist-info/entry_points.txt
uvhow-0.4.3.dist-info/METADATA
uvhow-0.4.3.dist-info/RECORD
