Metadata-Version: 2.3
Name: uvhow
Version: 0.4.3
Summary: Detect how uv was installed and get upgrade instructions
Keywords: uv,package-manager,cli,upgrade
Author: Tim Hopper
Author-email: Tim Hopper <tim@tdhopper.com>
Classifier: Development Status :: 4 - Beta
Classifier: Intended Audience :: Developers
Classifier: License :: OSI Approved :: MIT License
Classifier: Programming Language :: Python :: 3
Classifier: Programming Language :: Python :: 3.8
Classifier: Programming Language :: Python :: 3.9
Classifier: Programming Language :: Python :: 3.10
Classifier: Programming Language :: Python :: 3.11
Classifier: Programming Language :: Python :: 3.12
Classifier: Programming Language :: Python :: 3.13
Classifier: Topic :: Software Development :: Libraries :: Python Modules
Classifier: Topic :: System :: Installation/Setup
Requires-Python: >=3.8
